.gitignore
Makefile
README.rst
setup.py
cleese/__init__.py
cleese/executer.py
cleese/status.py
cleese/subprocess.py
cleese.egg-info/PKG-INFO
cleese.egg-info/SOURCES.txt
cleese.egg-info/dependency_links.txt
cleese.egg-info/top_level.txt
debian/NEWS
debian/changelog
debian/compat
debian/control
debian/copyright
debian/docs
debian/install
debian/manpages
debian/pycompat
debian/pyversions
debian/rules
tests/functional/__init__.py
tests/functional/test_advanced_commands.py
tests/functional/test_simple_commands.py
tests/unit/__init__.py