Metadata-Version: 1.0
Name: cleese
Version: 0.2.1
Summary: cleese is a shell command executer for python applications.
Home-page: http://www.cleese.org
Author: Bernardo Heynemann
Author-email: heynemann@gmail.com
License: OSI
Keywords: Popen process execution
Platform: UNKNOWN
Classifier: Development Status :: 4 - Beta
Classifier: Intended Audience :: Developers
Classifier: License :: OSI Approved
Classifier: Natural Language :: English
Classifier: Natural Language :: Portuguese (Brazilian)
Classifier: Operating System :: MacOS
Classifier: Operating System :: Microsoft :: Windows
Classifier: Operating System :: POSIX :: Linux
Classifier: Programming Language :: Python :: 2.5
Classifier: Programming Language :: Python :: 2.6
Classifier: Topic :: Software Development :: Quality Assurance
Classifier: Topic :: Software Development :: Testing
